{"cameraMode":{"drawMode":0,"name":"Shaded","section":"Shading Mode"},"sceneLighting":false,"audioPlay":false,"sceneViewState":{"m_AlwaysRefresh":false,"showFog":true,"showSkybox":false,"showFlares":true,"showImageEffects":true,"showParticleSystems":true,"showVisualEffectGraphs":true,"m_FxEnabled":true},"in2DMode":false,"pivot":{"x":8.23783016204834,"y":-4.570452690124512,"z":0.22514940798282624},"rotation":{"x":0.12420210242271424,"y":0.749390721321106,"z":-0.14687348902225495,"w":0.6339815258979797},"size":7.632352828979492,"orthographic":false}